pulse_executor/__init__.py
pulse_executor/cli.py
pulse_executor/executor.py
pulse_executor/status.py
pulse_executor-0.0.1.dist-info/LICENSE
pulse_executor-0.0.1.dist-info/METADATA
pulse_executor-0.0.1.dist-info/WHEEL
pulse_executor-0.0.1.dist-info/entry_points.txt
pulse_executor-0.0.1.dist-info/top_level.txt
pulse_executor-0.0.1.dist-info/RECORD
