Metadata-Version: 2.1
Name: pulse-executor
Version: 0.0.1
Summary: Pulse Program Executor
Home-page: https://rozum.com
Author: Rozum Robotics
Author-email: dev@rozum.com
License: Apache License 2.0
Platform: UNKNOWN
Classifier: License :: OSI Approved :: Apache Software License
Classifier: Development Status :: 5 - Production/Stable
Classifier: Programming Language :: Python
Classifier: Programming Language :: Python :: 3
Classifier: Programming Language :: Python :: Implementation :: CPython
